RISCVProcessor/lab5.srcs/sources_1/new/Mux.v
`timescale 1ns / 1ps
//////////////////////////////////////////////////////////////////////////////////
// Company: 
// Engineer: 
// 
// Create Date: 06/02/2024 09:29:05 PM
// Design Name: 
// Module Name: MUX
// Project Name: 
// Target Devices: 
// Tool Versions: 
// Description: 
// 
// Dependencies: 
// 
// Revision:
// Revision 0.01 - File Created
// Additional Comments:
// 
//////////////////////////////////////////////////////////////////////////////////


module MUX #(
    parameter SIZE = 32
    )
    (
        input wire [SIZE-1:0] A_in,
        input wire [SIZE-1:0] B_in,
        input wire Sel,
        output wire [SIZE-1:0] out
    );
    assign out = (Sel)? A_in : B_in;
endmodule

RISCVProcessor/lab5.srcs/sources_1/new/DataMem.v
`timescale 1ns / 1ps
//////////////////////////////////////////////////////////////////////////////////
// Company: 
// Engineer: 
// 
// Create Date: 05/31/2024 12:57:40 PM
// Design Name: 
// Module Name: DataMem
// Project Name: 
// Target Devices: 
// Tool Versions: 
// Description: 
// 
// Dependencies: 
// 
// Revision:
// Revision 0.01 - File Created
// Additional Comments:
// 
//////////////////////////////////////////////////////////////////////////////////


module DataMem(input MemRead, 
               input MemWrite, 
               input [8:0] addr, 
               input [31:0] write_data, 
               output [31:0] read_data);
    reg [31:0] data_mem [127:0];
    
    assign read_data = (MemRead)? data_mem[addr[8:2]] : 32'bX;
    always @(write_data, addr, MemWrite)
    begin
        if (MemWrite == 1'b1)
        begin
            data_mem[addr[8:2]] = write_data;
        end
    end
endmodule

RISCVProcessor/lab5.srcs/sources_1/new/ALU.v
`timescale 1ns / 1ps
//////////////////////////////////////////////////////////////////////////////////
// Company: 
// Engineer: 
// 
// Create Date: 05/31/2024 01:12:27 PM
// Design Name: 
// Module Name: ALU_32
// Project Name: 
// Target Devices: 
// Tool Versions: 
// Description: 
// 
// Dependencies: 
// 
// Revision:
// Revision 0.01 - File Created
// Additional Comments:
// 
//////////////////////////////////////////////////////////////////////////////////


module ALU_32(
    input [31:0] A_in, B_in,
    input [3:0] ALU_Sel,
    output [31:0] ALU_Out,
    output reg Carry_Out,
    output Zero,
    output reg Overflow = 1'b0
    );
    reg [31:0] ALU_Result;
    reg [32:0] temp;
    reg [32:0] twos_com;
    
    assign ALU_Out = ALU_Result;
    assign Zero = (ALU_Result == 0);
    
    always @(*)
    begin
        Overflow = 1'b0;
        Carry_Out = 1'b0;
        case(ALU_Sel)
            4'b0000:
                ALU_Result = A_in & B_in;
            4'b0001:
                ALU_Result = A_in | B_in;
            4'b0010:
            begin
                ALU_Result = $signed(A_in) + $signed(B_in);
                temp = {1'b0, A_in} + {1'b0, B_in};
                Carry_Out = temp[32];
                if ((A_in[31] & B_in[31] & ~ALU_Out[31]) | (~A_in[31] & ~B_in[31] & ALU_Out[31]))
                    Overflow = 1'b1;
                else
                    Overflow = 1'b0;
            end
            4'b0110:
            begin
                ALU_Result = $signed(A_in) - $signed(B_in);
                twos_com = ~(B_in) + 1'b1;
                
                if ((A_in[31] & twos_com[31] & ~ALU_Out[31]) | (~A_in[31] & ~twos_com[31] & ALU_Out[31]))
                    Overflow = 1'b1;
                else
                    Overflow = 1'b0; 
            end
            4'b0111:
                ALU_Result = ($signed(A_in) < $signed(B_in))? 32'd1: 32'd0;
            4'b1100:
                ALU_Result = ~(A_in | B_in);
            4'b1111:
                ALU_Result = (A_in == B_in)? 32'd1: 32'd0;
            default:
                ALU_Result = A_in + B_in;
        endcase
    end
endmodule

RISCVProcessor/lab5.srcs/sources_1/new/ImmGen.v
`timescale 1ns / 1ps
//////////////////////////////////////////////////////////////////////////////////
// Company: 
// Engineer: 
// 
// Create Date: 05/15/2024 12:14:33 PM
// Design Name: 
// Module Name: ImmGen
// Project Name: 
// Target Devices: 
// Tool Versions: 
// Description: 
// 
// Dependencies: 
// 
// Revision:
// Revision 0.01 - File Created
// Additional Comments:
// 
//////////////////////////////////////////////////////////////////////////////////


module ImmGen(
    input [31:0] InstCode,
    output reg [31:0] ImmOut
    );
    
    always @(InstCode)
    begin
        case (InstCode[6:0])
            7'b0000011: // I-type load
                ImmOut = {InstCode[31]? {20{1'b1}}:20'b0, InstCode[31:20]};
            7'b0010011: // I-type non-load
                ImmOut = {InstCode[31]? {20{1'b1}}:20'b0, InstCode[31:20]};
            7'b0100011: // S-type Store
                ImmOut = {InstCode[31]? {20{1'b1}}:20'b0, InstCode[31:25], InstCode[11:7]};
            7'b0010111: // U-type
                ImmOut = {InstCode[31:12], 12'b0};
            default:
                ImmOut = 32'b0;
        endcase
    end
endmodule

RISCVProcessor/lab5.srcs/sources_1/new/RegFile.v
`timescale 1ns / 1ps
//////////////////////////////////////////////////////////////////////////////////
// Company: 
// Engineer: 
// 
// Create Date: 05/15/2024 12:14:33 PM
// Design Name: 
// Module Name: RegFile
// Project Name: 
// Target Devices: 
// Tool Versions: 
// Description: 
// 
// Dependencies: 
// 
// Revision:
// Revision 0.01 - File Created
// Additional Comments:
// 
//////////////////////////////////////////////////////////////////////////////////


module RegFile(
    input clk,
    input reset,
    input rg_wrt_en,
    input [4:0] rg_rd_addr1,
    input [4:0] rg_rd_addr2,
    input [4:0] rg_wrt_addr,
    input [31:0] rg_wrt_data,
    output [31:0] rg_rd_data1,
    output [31:0] rg_rd_data2
    );
    reg [31:0] regfile [31:0];
    initial
    begin
            regfile[0] <= 32'h0;
            regfile[1] <= 32'h0;
            regfile[2] <= 32'h0;
            regfile[3] <= 32'h0;
            regfile[4] <= 32'h0;
            regfile[5] <= 32'h0;
            regfile[6] <= 32'h0;
            regfile[7] <= 32'h0;
            regfile[8] <= 32'h0;
            regfile[9] <= 32'h0;
            regfile[10] <= 32'h0;
            regfile[11] <= 32'h0;
            regfile[12] <= 32'h0;
            regfile[13] <= 32'h0;
            regfile[14] <= 32'h0;
            regfile[15] <= 32'h0;
            regfile[16] <= 32'h0;
            regfile[17] <= 32'h0;
            regfile[18] <= 32'h0;
            regfile[19] <= 32'h0;
            regfile[20] <= 32'h0;
            regfile[21] <= 32'h0;
            regfile[22] <= 32'h0;
            regfile[23] <= 32'h0;
            regfile[24] <= 32'h0;
            regfile[25] <= 32'h0;
            regfile[26] <= 32'h0;
            regfile[27] <= 32'h0;
            regfile[28] <= 32'h0;
            regfile[29] <= 32'h0;
            regfile[30] <= 32'h0;
            regfile[31] <= 32'h0;
    end
    
    always @(posedge reset, posedge clk)
    begin
        if (reset == 1'b1)
        begin
            regfile[0] <= 32'h0;
            regfile[1] <= 32'h0;
            regfile[2] <= 32'h0;
            regfile[3] <= 32'h0;
            regfile[4] <= 32'h0;
            regfile[5] <= 32'h0;
            regfile[6] <= 32'h0;
            regfile[7] <= 32'h0;
            regfile[8] <= 32'h0;
            regfile[9] <= 32'h0;
            regfile[10] <= 32'h0;
            regfile[11] <= 32'h0;
            regfile[12] <= 32'h0;
            regfile[13] <= 32'h0;
            regfile[14] <= 32'h0;
            regfile[15] <= 32'h0;
            regfile[16] <= 32'h0;
            regfile[17] <= 32'h0;
            regfile[18] <= 32'h0;
            regfile[19] <= 32'h0;
            regfile[20] <= 32'h0;
            regfile[21] <= 32'h0;
            regfile[22] <= 32'h0;
            regfile[23] <= 32'h0;
            regfile[24] <= 32'h0;
            regfile[25] <= 32'h0;
            regfile[26] <= 32'h0;
            regfile[27] <= 32'h0;
            regfile[28] <= 32'h0;
            regfile[29] <= 32'h0;
            regfile[30] <= 32'h0;
            regfile[31] <= 32'h0;
        end
        if (rg_wrt_en == 1'b1)
        begin
            regfile[rg_wrt_addr] = rg_wrt_data;
        end
    end
    assign rg_rd_data1 = regfile[rg_rd_addr1];
    assign rg_rd_data2 = regfile[rg_rd_addr2];
endmodule

RISCVProcessor/lab5.srcs/sources_1/new/InstMem.v
`timescale 1ns / 1ps
//////////////////////////////////////////////////////////////////////////////////
// Company: 
// Engineer: 
// 
// Create Date: 05/15/2024 12:14:33 PM
// Design Name: 
// Module Name: InstMem
// Project Name: 
// Target Devices: 
// Tool Versions: 
// Description: 
// 
// Dependencies: 
// 
// Revision:
// Revision 0.01 - File Created
// Additional Comments:
// 
//////////////////////////////////////////////////////////////////////////////////


module InstMem(
    input [7:0] addr,
    output [31:0] instruction
    );
    reg [31:0] memory [19:0];
    initial
    begin
        memory[0] = 32'h00007033; // and x0 , x0 , x0         32'h00000000
        memory[1] = 32'h00100093; // addi x1 , x0 , 1         32'h00000001
        memory[2] = 32'h00200113; // addi x2 , x0 , 2         32'h00000002
        memory[3] = 32'h00308193; // addi x3 , x1 , 3         32'h00000004
        memory[4] = 32'h00408213; // addi x4 , x1 , 4         32'h00000005
        memory[5] = 32'h00510293; // addi x5 , x2 , 5         32'h00000007
        memory[6] = 32'h00610313; // addi x6 , x2 , 6         32'h00000008
        memory[7] = 32'h00718393; // addi x7 , x3 , 7         32'h0000000B
        memory[8] = 32'h00208433; // add x8 , x1 , x2         32'h00000003
        memory[9] = 32'h404404b3; // sub x9 , x8 , x4         32'hfffffffe
        memory[10] = 32'h00317533; // and x10 , x2 , x3       32'h00000000
        memory[11] = 32'h0041e5b3; // or x11 , x3 , x4        32'h00000005
        memory[12] = 32'h0041a633; // if x3 is less than x4 , then x12 = 1
                                   //                         32'h00000001
        memory[13] = 32'h007346b3; // nor x13 , x6 , x7       32'hfffffff4
        memory[14] = 32'h4d34f713; // andi x14 , x9 , "4D3"   32'h000004d2
        memory[15] = 32'h8d35e793; // ori x15 , x11 , "8D3"   32'hfffff8d7
        memory[16] = 32'h4d26a813; // if x13 is less than 32'h000004d2 , then x16 = 1
                                   //                         32'h00000000
        memory[17] = 32'h4d244893; // nori x17 , x8 , "4D2"   32'hfffffb2c
        memory[18] = 32'h02b02823;
        memory[19] = 32'h03002603;
    end
    assign instruction = memory[addr[7:2]];
    
endmodule

RISCVProcessor/lab5.srcs/sources_1/new/FlipFlop.v
`timescale 1ns / 1ps
//////////////////////////////////////////////////////////////////////////////////
// Company: 
// Engineer: 
// 
// Create Date: 05/15/2024 12:14:33 PM
// Design Name: 
// Module Name: FlipFlop
// Project Name: 
// Target Devices: 
// Tool Versions: 
// Description: 
// 
// Dependencies: 
// 
// Revision:
// Revision 0.01 - File Created
// Additional Comments:
// 
//////////////////////////////////////////////////////////////////////////////////


module FlipFlop(
    input clk,
    input reset,
    input [7:0] d,
    output reg [7:0] q
    );
    
    always @(posedge clk)
    begin
        if (reset == 1)
            q <= 8'b0;
        else
            q <= d;
    end
endmodule

RISCVProcessor/lab5.srcs/sources_1/new/Datapath.v
`timescale 1ns / 1ps
//////////////////////////////////////////////////////////////////////////////////
// Company: 
// Engineer: 
// 
// Create Date: 05/31/2024 01:34:34 PM
// Design Name: 
// Module Name: data_path
// Project Name: 
// Target Devices: 
// Tool Versions: 
// Description: 
// 
// Dependencies: 
// 
// Revision:
// Revision 0.01 - File Created
// Additional Comments:
// 
//////////////////////////////////////////////////////////////////////////////////


module data_path #(
    parameter PC_W = 8,
    parameter INS_W = 32,
    parameter RF_ADDRESS = 5,
    parameter DATA_W = 32,
    parameter DM_ADDRESS = 9,
    parameter ALU_CC_W = 4
    )
    (
    input clk,
    input reset,
    input reg_write,
    input mem2reg,
    input alu_src,
    input mem_write,
    input mem_read,
    input [ALU_CC_W-1:0] alu_cc,
    output [6:0] opcode,
    output [6:0] funct7,
    output [2:0] funct3,
    output [DATA_W-1:0] alu_result
    );
    // Program Counter
    wire [PC_W-1:0] PC, PCPlus4;
    assign PCPlus4 = PC + 4;
    FlipFlop ProgramCounter(clk, reset, PCPlus4, PC);
    
    // Instruction Memory
    wire [INS_W-1:0] Instruction;
    InstMem ReadInstruction(PC, Instruction);
    assign opcode = Instruction[6:0];
    assign funct3 = Instruction[14:12];
    assign funct7 = Instruction[31:25];
    
    // Register File
    wire [RF_ADDRESS-1:0] RdAddr1;
    wire [RF_ADDRESS-1:0] RdAddr2;
    wire [RF_ADDRESS-1:0] WrtAddr;
    wire [DATA_W-1:0] Reg1;
    wire [DATA_W-1:0] Reg2;
    wire [DATA_W-1:0] WriteBack_Data;
    assign RdAddr1 = Instruction[19:15];
    assign RdAddr2 = Instruction[24:20];
    assign WrtAddr = Instruction[11:7];
    
    RegFile RegisterFile(
        .clk(clk),
        .reset(reset),
        .rg_wrt_en(reg_write),
        .rg_rd_addr1(RdAddr1),
        .rg_rd_addr2(RdAddr2),
        .rg_wrt_addr(WrtAddr),
        .rg_wrt_data(WriteBack_Data),
        .rg_rd_data1(Reg1),
        .rg_rd_data2(Reg2)
    );
    
    // ImmGenerator
    wire [DATA_W-1:0] ExtImm;
    ImmGen ImmediateGenerator(Instruction, ExtImm);
    
    // ALUSrc MUX
    wire [DATA_W-1:0] SrcB;
    wire Carry_Out, Zero, Overflow;
    MUX srcb(ExtImm, Reg2, alu_src, SrcB);
    
    // ALU
    ALU_32 ALU(
    .A_in(Reg1),
    .B_in(SrcB),
    .ALU_Sel(alu_cc),
    .ALU_Out(alu_result),
    .Carry_Out(Carry_Out),
    .Zero(Zero),
    .Overflow(Overflow)
    );
    
    // data_mem
    wire [DATA_W-1:0] DataMem_read;
    wire [DM_ADDRESS-1:0] DM_Address;
    assign DM_Address = alu_result[8:0];
    DataMem DataMemory(mem_read, mem_write, DM_Address, Reg2, DataMem_read);
    
    // WriteBack MUX
    MUX writeback(DataMem_read, alu_result, mem2reg, WriteBack_Data);
    
endmodule

RISCVProcessor/lab5.srcs/sources_1/new/ALUController.v
`timescale 1ns / 1ps
//////////////////////////////////////////////////////////////////////////////////
// Company: 
// Engineer: 
// 
// Create Date: 06/02/2024 10:05:40 PM
// Design Name: 
// Module Name: ALUController
// Project Name: 
// Target Devices: 
// Tool Versions: 
// Description: 
// 
// Dependencies: 
// 
// Revision:
// Revision 0.01 - File Created
// Additional Comments:
// 
//////////////////////////////////////////////////////////////////////////////////


module ALUController(
    input [2:0] ALUOp,
    input [6:0] Funct7,
    input [2:0] Funct3,
    output reg [3:0] Operation 
    );
    always @(*)
    begin
        case (Funct7)
            7'b0000000:
            begin
                case ({Funct3, ALUOp})
                    5'b11110: Operation = 4'b0000; // AND
                    5'b11010: Operation = 4'b0001; // OR
                    5'b10010: Operation = 4'b1100; // NOR
                    5'b01010: Operation = 4'b0111; // SLT
                    5'b00010: Operation = 4'b0010; // ADD
                endcase
            end
            7'b0100000:
            begin
                if ({Funct3, ALUOp} == 5'b00010) Operation = 4'b0110;
                else Operation = 4'bXXXX;
            end
            default:
            begin
                case ({Funct3, ALUOp})
                    5'b11100: Operation = 4'b0000; // ANDI
                    5'b11000: Operation = 4'b0001; // ORI
                    5'b10000: Operation = 4'b1100; // NORI
                    5'b01000: Operation = 4'b0010; // SLTI
                    5'b00000: Operation = 4'b0010; // ADDI
                    5'b01001: Operation = 4'b0010; // LW
                    5'b01001: Operation = 4'b0010; // SW
                    default: Operation = 4'bXXXX;
                endcase
            end
        endcase
    end
endmodule

RISCVProcessor/lab5.srcs/sources_1/new/Controller.v
`timescale 1ns / 1ps
//////////////////////////////////////////////////////////////////////////////////
// Company: 
// Engineer: 
// 
// Create Date: 06/02/2024 09:52:03 PM
// Design Name: 
// Module Name: Controller
// Project Name: 
// Target Devices: 
// Tool Versions: 
// Description: 
// 
// Dependencies: 
// 
// Revision:
// Revision 0.01 - File Created
// Additional Comments:
// 
//////////////////////////////////////////////////////////////////////////////////


module Controller(
    input [6:0] Opcode,
    output [1:0] ALUOp,
    output RegWrite, ALUSrc, MemRead, MemWrite, MemtoReg
    );
    parameter LW = 7'b0000011;
    parameter SW = 7'b0100011;
    parameter I = 7'b0010011;
    parameter NOT_I = 7'b0110011;
    assign MemtoReg = (Opcode == LW)? 1'b1 : 1'b0;
    assign MemWrite = (Opcode == SW)? 1'b1 : 1'b0;
    assign MemRead = (Opcode == LW)? 1'b1 : 1'b0;
    assign ALUSrc = (Opcode == NOT_I)? 1'b0 : 1'b1;
    assign RegWrite = (Opcode == SW)? 1'b0 : 1'b1;
    
    assign ALUOp = (Opcode == NOT_I)? 2'b10 :
                   ((Opcode == I)? 2'b00 : 2'b01);
endmodule

RISCVProcessor/lab5.srcs/sources_1/new/processor.v
`timescale 1ns / 1ps
//////////////////////////////////////////////////////////////////////////////////
// Company: 
// Engineer: 
// 
// Create Date: 06/02/2024 10:35:14 PM
// Design Name: 
// Module Name: processor
// Project Name: 
// Target Devices: 
// Tool Versions: 
// Description: 
// 
// Dependencies: 
// 
// Revision:
// Revision 0.01 - File Created
// Additional Comments:
// 
//////////////////////////////////////////////////////////////////////////////////


module processor(
    input clk, reset,
    output [31:0] Result
    );
    wire [2:0] Funct3;
    wire [6:0] Funct7;
    wire [6:0] Opcode;
    wire [2:0] ALUOp;
    wire [3:0] Operation;
    
    wire RegWrite, ALUSrc, MemRead, MemWrite, MemtoReg;
    Controller controller(Opcode, ALUOp, RegWrite, ALUSrc, MemRead, MemWrite, MemtoReg);
    ALUController alucontroller(ALUOp, Funct7, Funct3, Operation);
    data_path datapath(clk, reset, RegWrite, MemtoReg, ALUSrc, MemWrite, MemRead, Operation, Opcode, Funct7, Funct3, Result);
    
endmodule

RISCVProcessor/lab5.srcs/sim_1/new/tb_processor.v
`timescale 1ns / 1ps
//////////////////////////////////////////////////////////////////////////////////
// Company: 
// Engineer: 
// 
// Create Date: 06/03/2024 11:01:40 PM
// Design Name: 
// Module Name: tb_processor
// Project Name: 
// Target Devices: 
// Tool Versions: 
// Description: 
// 
// Dependencies: 
// 
// Revision:
// Revision 0.01 - File Created
// Additional Comments:
// 
//////////////////////////////////////////////////////////////////////////////////


module tb_processor();
    reg clk, rst;
    wire [31:0] tb_Result;
    processor processor_inst(clk, rst, tb_Result);
    always
    begin
        #10;
        clk = ~clk;
    end
    initial
    begin
    clk = 0;
    @(posedge clk); rst = 1;
    @(posedge clk); rst = 0;
    end
    
    initial begin
        $dumpfile("test.vcd"); $dumpvars;
    end
    
    integer point = 0;
    always @(*)
    begin
        #20;
        if (tb_Result == 32'h00000000)
        begin
            point = point + 1;
        end
        
        #20;
        if (tb_Result == 32'h00000001)
        begin
            point = point + 1;
        end
        
        #20;
        if (tb_Result == 32'h00000002)
        begin
            point = point + 1;
        end
        
        #20;
        if (tb_Result == 32'h00000004)
        begin
            point = point + 1;
        end
        
        #20;
        if (tb_Result == 32'h00000005)
        begin
            point = point + 1;
        end
        
        #20;
        if (tb_Result == 32'h00000007)
        begin
            point = point + 1;
        end
        
        #20;
        if (tb_Result == 32'h00000008)
        begin
            point = point + 1;
        end
        
        #20;
        if (tb_Result == 32'h0000000b)
        begin
            point = point + 1;
        end
        
        #20;
        if (tb_Result == 32'h00000003)
        begin
            point = point + 1;
        end
        
        #20;
        if (tb_Result == 32'hfffffffe)
        begin
            point = point + 1;
        end
        
        #20;
        if (tb_Result == 32'h00000000)
        begin
            point = point + 1;
        end
        
        #20;
        if (tb_Result == 32'h00000005)
        begin
            point = point + 1;
        end
        
        #20;
        if (tb_Result == 32'h00000001)
        begin
            point = point + 1;
        end
        
        #20;
        if (tb_Result == 32'hfffffff4)
        begin
            point = point + 1;
        end
        
        #20;
        if (tb_Result == 32'h000004D2)
        begin
            point = point + 1;
        end
        
        #20;
        if (tb_Result == 32'hfffff8d7)
        begin
            point = point + 1;
        end
        
        #20;
        if (tb_Result == 32'h00000001)
        begin
            point = point + 1;
        end
        
        #20;
        if (tb_Result == 32'hfffffb2c)
        begin
            point = point + 1;
        end
        
        #20;
        if (tb_Result == 32'h00000030)
        begin
            point = point + 1;
        end
        
        #20;
        if (tb_Result == 32'h00000030)
        begin
            point = point + 1;
        end
        
        $display("%s%d","The number of correct test cases is :", point);
    end
    
    initial begin
        #430;
    end
endmodule

RISCVProcessor/lab5.sim/sim_1/behav/xsim/test.vcd
$date
   Wed Jun  5 23:36:54 2024
$end

$version
  2023.2
  $dumpfile ("test.vcd") 
$end

$timescale
  1ps
$end

$scope module tb_processor $end
$var reg 1 ! clk $end
$var reg 1 " rst $end
$var wire 32 # tb_Result [31:0] $end
$var integer 32 $ point [31:0] $end
$scope module processor_inst $end
$var wire 1 % clk $end
$var wire 1 & reset $end
$var wire 32 # Result [31:0] $end
$var wire 3 ' Funct3 [2:0] $end
$var wire 7 ( Funct7 [6:0] $end
$var wire 7 ) Opcode [6:0] $end
$var wire 3 * ALUOp [2:0] $end
$var wire 4 + Operation [3:0] $end
$var wire 1 , RegWrite $end
$var wire 1 - ALUSrc $end
$var wire 1 . MemRead $end
$var wire 1 / MemWrite $end
$var wire 1 0 MemtoReg $end
$scope module controller $end
$var wire 7 ) Opcode [6:0] $end
$var wire 2 1 ALUOp [1:0] $end
$var wire 1 , RegWrite $end
$var wire 1 - ALUSrc $end
$var wire 1 . MemRead $end
$var wire 1 / MemWrite $end
$var wire 1 0 MemtoReg $end
$upscope $end
$scope module alucontroller $end
$var wire 3 * ALUOp [2:0] $end
$var wire 7 ( Funct7 [6:0] $end
$var wire 3 ' Funct3 [2:0] $end
$var reg 4 2 Operation [3:0] $end
$upscope $end
$scope module datapath $end
$var wire 1 % clk $end
$var wire 1 & reset $end
$var wire 1 , reg_write $end
$var wire 1 0 mem2reg $end
$var wire 1 - alu_src $end
$var wire 1 / mem_write $end
$var wire 1 . mem_read $end
$var wire 4 + alu_cc [3:0] $end
$var wire 7 ) opcode [6:0] $end
$var wire 7 ( funct7 [6:0] $end
$var wire 3 ' funct3 [2:0] $end
$var wire 32 # alu_result [31:0] $end
$var wire 8 3 PC [7:0] $end
$var wire 8 4 PCPlus4 [7:0] $end
$var wire 32 5 Instruction [31:0] $end
$var wire 5 6 RdAddr1 [4:0] $end
$var wire 5 7 RdAddr2 [4:0] $end
$var wire 5 8 WrtAddr [4:0] $end
$var wire 32 9 Reg1 [31:0] $end
$var wire 32 : Reg2 [31:0] $end
$var wire 32 ; WriteBack_Data [31:0] $end
$var wire 32 < ExtImm [31:0] $end
$var wire 32 = SrcB [31:0] $end
$var wire 1 > Carry_Out $end
$var wire 1 ? Zero $end
$var wire 1 @ Overflow $end
$var wire 32 A DataMem_read [31:0] $end
$var wire 9 B DM_Address [8:0] $end
$scope module ProgramCounter $end
$var wire 1 % clk $end
$var wire 1 & reset $end
$var wire 8 4 d [7:0] $end
$var reg 8 C q [7:0] $end
$upscope $end
$scope module ReadInstruction $end
$var wire 8 3 addr [7:0] $end
$var wire 32 5 instruction [31:0] $end
$upscope $end
$scope module RegisterFile $end
$var wire 1 % clk $end
$var wire 1 & reset $end
$var wire 1 , rg_wrt_en $end
$var wire 5 6 rg_rd_addr1 [4:0] $end
$var wire 5 7 rg_rd_addr2 [4:0] $end
$var wire 5 8 rg_wrt_addr [4:0] $end
$var wire 32 ; rg_wrt_data [31:0] $end
$var wire 32 9 rg_rd_data1 [31:0] $end
$var wire 32 : rg_rd_data2 [31:0] $end
$upscope $end
$scope module ImmediateGenerator $end
$var wire 32 5 InstCode [31:0] $end
$var reg 32 D ImmOut [31:0] $end
$upscope $end
$scope module srcb $end
$var wire 32 < A_in [31:0] $end
$var wire 32 : B_in [31:0] $end
$var wire 1 - Sel $end
$var wire 32 = out [31:0] $end
$upscope $end
$scope module ALU $end
$var wire 32 9 A_in [31:0] $end
$var wire 32 = B_in [31:0] $end
$var wire 4 + ALU_Sel [3:0] $end
$var wire 32 # ALU_Out [31:0] $end
$var reg 1 E Carry_Out $end
$var wire 1 ? Zero $end
$var reg 1 F Overflow $end
$var reg 32 G ALU_Result [31:0] $end
$var reg 33 H temp [32:0] $end
$var reg 33 I twos_com [32:0] $end
$upscope $end
$scope module DataMemory $end
$var wire 1 . MemRead $end
$var wire 1 / MemWrite $end
$var wire 9 B addr [8:0] $end
$var wire 32 : write_data [31:0] $end
$var wire 32 A read_data [31:0] $end
$upscope $end
$scope module writeback $end
$var wire 32 A A_in [31:0] $end
$var wire 32 # B_in [31:0] $end
$var wire 1 0 Sel $end
$var wire 32 ; out [31:0] $end
$upscope $end
$upscope $end
$upscope $end
$upscope $end
$enddefinitions $end

#0
$dumpvars
0!
x"
bx #
b0 $
0%
x&
bx '
bx (
bx )
bzxx *
bx +
x,
x-
x.
x/
x0
bx 1
bx 2
bx 3
bx 4
bx 5
bx 6
bx 7
bx 8
bx 9
bx :
bx ;
bx <
bx =
x>
x?
0@
bx A
bx B
bx C
bx D
xE
0F
bx G
bx H
bx I
$end

#10000
1!
1"
b0 #
1%
1&
b111 '
b0 (
b110011 )
bz10 *
1,
0-
0.
0/
00
b10 1
b0 3
b100 4
b111000000110011 5
b0 6
b0 7
b0 8
b0 9
b0 :
b0 ;
b0 <
b0 =
0>
1?
b0 B
b0 C
b0 D
0E
b0 G

#20000
0!
b1 $
0%

#30000
1!
0"
b1 #
1%
0&
b0 '
b10011 )
bz00 *
1-
b0 1
b100 3
b1000 4
b100000000000010010011 5
b1 7
b1 8
b1 ;
b1 <
b1 =
0?
b1 B
b100 C
b1 D
b1 G

#40000
0!
b10 $
0%

#50000
1!
b10 #
1%
b1000 3
b1100 4
b1000000000000100010011 5
b10 7
b10 8
b0 :
b10 ;
b10 <
b10 =
b10 B
b1000 C
b10 D
b10 G

#60000
0!
b11 $
0%

#70000
1!
b100 #
1%
b1100 3
b10000 4
b1100001000000110010011 5
b1 6
b11 7
b11 8
b1 9
b0 :
b100 ;
b11 <
b11 =
b100 B
b1100 C
b11 D
b100 G

#80000
0!
b100 $
0%

#90000
1!
b101 #
1%
b10000 3
b10100 4
b10000001000001000010011 5
b100 7
b100 8
b0 :
b101 ;
b100 <
b100 =
b101 B
b10000 C
b100 D
b101 G

#100000
0!
b101 $
0%

#110000
1!
b111 #
1%
b10100 3
b11000 4
b10100010000001010010011 5
b10 6
b101 7
b101 8
b10 9
b0 :
b111 ;
b101 <
b101 =
b111 B
b10100 C
b101 D
b111 G

#120000
0!
b110 $
0%

#130000
1!
b1000 #
1%
b11000 3
b11100 4
b11000010000001100010011 5
b110 7
b110 8
b0 :
b1000 ;
b110 <
b110 =
b1000 B
b11000 C
b110 D
b1000 G

#140000
0!
b111 $
0%

#150000
1!
b1011 #
1%
b11100 3
b100000 4
b11100011000001110010011 5
b11 6
b111 7
b111 8
b100 9
b0 :
b1011 ;
b111 <
b111 =
b1011 B
b11100 C
b111 D
b1011 G

#160000
0!
b1000 $
0%

#170000
1!
b11 #
1%
b110011 )
bz10 *
0-
b10 1
b100000 3
b100100 4
b1000001000010000110011 5
b1 6
b10 7
b1000 8
b1 9
b10 :
b11 ;
b0 <
b10 =
b11 B
b100000 C
b0 D
b11 G

#180000
0!
b1001 $
0%

#190000
1!
b1000 #
1%
b100000 (
b100100 3
b101000 4
b1000000010001000000010010110011 5
b1000 6
b100 7
b1001 8
b11 9
b101 :
b1000 ;
b101 =
b1000 B
b100100 C
b1000 G

#200000
0!
0%

#210000
1!
b110 #
1%
b111 '
b0 (
b101000 3
b101100 4
b1100010111010100110011 5
b10 6
b11 7
b1010 8
b10 9
b100 :
b110 ;
b100 =
b110 B
b101000 C
b110 G

#220000
0!
0%

#230000
1!
b1001 #
1%
b110 '
b101100 3
b110000 4
b10000011110010110110011 5
b11 6
b100 7
b1011 8
b100 9
b101 :
b1001 ;
b101 =
b1001 B
b101100 C
b1001 G

#240000
0!
0%

#250000
1!
1%
b10 '
b110000 3
b110100 4
b10000011010011000110011 5
b1100 8
b110000 C

#260000
0!
0%

#270000
1!
b10011 #
1%
b100 '
b110100 3
b111000 4
b11100110100011010110011 5
b110 6
b111 7
b1101 8
b1000 9
b1011 :
b10011 ;
b1011 =
b10011 B
b110100 C
b10011 G

#280000
0!
0%

#290000
1!
b10011011011 #
1%
b111 '
b100110 (
b10011 )
bz00 *
1-
b0 1
b111000 3
b111100 4
b1001101001101001111011100010011 5
b1001 6
b10011 7
b1110 8
b0 :
b10011011011 ;
b10011010011 <
b10011010011 =
b11011011 B
b111000 C
b10011010011 D
b10011011011 G

#300000
0!
0%

#310000
1!
b11111111111111111111100011011100 #
1%
b110 '
b1000110 (
b111100 3
b1000000 4
b10001101001101011110011110010011 5
b1011 6
b1111 8
b1001 9
b11111111111111111111100011011100 ;
b11111111111111111111100011010011 <
b11111111111111111111100011010011 =
b11011100 B
b111100 C
b11111111111111111111100011010011 D
b11111111111111111111100011011100 G

#320000
0!
0%

#330000
1!
b10011100101 #
1%
b10 '
b100110 (
b1000000 3
b1000100 4
b1001101001001101010100000010011 5
b1101 6
b10010 7
b10000 8
b10011 9
b10011100101 ;
b10011010010 <
b10011010010 =
b11100101 B
b1000000 C
b10011010010 D
b10011100101 G

#340000
0!
0%

#350000
1!
b10011010101 #
1%
b100 '
b1000100 3
b1001000 4
b1001101001001000100100010010011 5
b1000 6
b10001 8
b11 9
b10011010101 ;
b11010101 B
b1000100 C
b10011010101 G

#360000
0!
0%

#370000
1!
b110000 #
1%
b10 '
b1 (
b100011 )
bz01 *
0,
1/
b1 1
b1001000 3
b1001100 4
b10101100000010100000100011 5
b0 6
b1011 7
b10000 8
b0 9
b1001 :
b110000 ;
b110000 <
b110000 =
b110000 B
b1001000 C
b110000 D
b110000 G

#380000
0!
b1010 $
0%

#390000
1!
1%
b11 )
1,
1.
0/
10
b1001100 3
b1010000 4
b11000000000010011000000011 5
b10000 7
b1100 8
b10011100101 :
b1001 ;
b1001 A
b1001100 C

#400000
0!
b1011 $
0%

#410000
1!
bx #
1%
bx '
bx (
bx )
bzxx *
x,
x-
x.
x/
x0
bx 1
b1010000 3
b1010100 4
bx 5
bx 6
bx 7
bx 8
bx 9
bx :
bx ;
b0 <
bx =
x?
bx A
bx B
b1010000 C
b0 D
bx G

#420000
0!
0%

#430000
1!
1%
b1010100 3
b1011000 4
b1010100 C

#440000
0!
0%

#450000
1!
1%
b1011000 3
b1011100 4
b1011000 C

#460000
0!
0%

#470000
1!
1%
b1011100 3
b1100000 4
b1011100 C

